[
    {
        "Titulo": "Mundo Jurasico",
        "Director": "Vin Diesel",
        "Genero": "Ciencia Ficcion",
        "Valoracion": 9.0
    },
    {
        "Titulo": "Ready Player One",
        "Director": "Saber",
        "Genero": "Ciencia Ficcion",
        "Valoracion": 9.0
    },
    {
        "Titulo": "Invicto",
        "Director": "Skot Adkins",
        "Genero": "Lucha",
        "Valoracion": 10.0
    },
    {
        "Titulo": "La Gran Muralla China",
        "Director": "Xhian Chi",
        "Genero": "Ficcion",
        "Valoracion": 10.0
    }
]